<?xml version='1.0' encoding='UTF-8'?>
<annotation>
	<folder />
	<filename />
	<path />
	<source>
		<database>unknown</database>
	</source>
	<size>
		<width>1716</width>
		<height>942</height>
		<depth>3</depth>
	</size>
	<segmented>0</segmented>
	<object>
		<name>stas</name>
		<pose>unspecified</pose>
		<truncated>1</truncated>
		<difficult>0</difficult>
		<bndbox>
			<xmin>160</xmin>
			<ymin>1</ymin>
			<xmax>285</xmax>
			<ymax>44</ymax>
		</bndbox>
	</object>
	<object>
		<name>stas</name>
		<pose>unspecified</pose>
		<truncated>0</truncated>
		<difficult>0</difficult>
		<bndbox>
			<xmin>172</xmin>
			<ymin>140</ymin>
			<xmax>230</xmax>
			<ymax>206</ymax>
		</bndbox>
	</object>
	<object>
		<name>stas</name>
		<pose>unspecified</pose>
		<truncated>0</truncated>
		<difficult>0</difficult>
		<bndbox>
			<xmin>230</xmin>
			<ymin>136</ymin>
			<xmax>306</xmax>
			<ymax>227</ymax>
		</bndbox>
	</object>
	<object>
		<name>stas</name>
		<pose>unspecified</pose>
		<truncated>0</truncated>
		<difficult>0</difficult>
		<bndbox>
			<xmin>940</xmin>
			<ymin>805</ymin>
			<xmax>994</xmax>
			<ymax>868</ymax>
		</bndbox>
	</object>
	<object>
		<name>stas</name>
		<pose>unspecified</pose>
		<truncated>0</truncated>
		<difficult>0</difficult>
		<bndbox>
			<xmin>833</xmin>
			<ymin>827</ymin>
			<xmax>878</xmax>
			<ymax>859</ymax>
		</bndbox>
	</object>
	<object>
		<name>stas</name>
		<pose>unspecified</pose>
		<truncated>0</truncated>
		<difficult>0</difficult>
		<bndbox>
			<xmin>295</xmin>
			<ymin>734</ymin>
			<xmax>420</xmax>
			<ymax>863</ymax>
		</bndbox>
	</object>
	<object>
		<name>stas</name>
		<pose>unspecified</pose>
		<truncated>0</truncated>
		<difficult>0</difficult>
		<bndbox>
			<xmin>339</xmin>
			<ymin>863</ymin>
			<xmax>438</xmax>
			<ymax>928</ymax>
		</bndbox>
	</object>
	<object>
		<name>stas</name>
		<pose>unspecified</pose>
		<truncated>0</truncated>
		<difficult>0</difficult>
		<bndbox>
			<xmin>1219</xmin>
			<ymin>831</ymin>
			<xmax>1272</xmax>
			<ymax>892</ymax>
		</bndbox>
	</object>
	<object>
		<name>stas</name>
		<pose>unspecified</pose>
		<truncated>0</truncated>
		<difficult>0</difficult>
		<bndbox>
			<xmin>165</xmin>
			<ymin>401</ymin>
			<xmax>252</xmax>
			<ymax>472</ymax>
		</bndbox>
	</object>
	<object>
		<name>stas</name>
		<pose>unspecified</pose>
		<truncated>0</truncated>
		<difficult>0</difficult>
		<bndbox>
			<xmin>650</xmin>
			<ymin>221</ymin>
			<xmax>694</xmax>
			<ymax>259</ymax>
		</bndbox>
	</object>
	<object>
		<name>stas</name>
		<pose>unspecified</pose>
		<truncated>0</truncated>
		<difficult>0</difficult>
		<bndbox>
			<xmin>675</xmin>
			<ymin>248</ymin>
			<xmax>721</xmax>
			<ymax>288</ymax>
		</bndbox>
	</object>
	<object>
		<name>stas</name>
		<pose>unspecified</pose>
		<truncated>0</truncated>
		<difficult>0</difficult>
		<bndbox>
			<xmin>744</xmin>
			<ymin>273</ymin>
			<xmax>786</xmax>
			<ymax>296</ymax>
		</bndbox>
	</object>
	<object>
		<name>stas</name>
		<pose>unspecified</pose>
		<truncated>0</truncated>
		<difficult>0</difficult>
		<bndbox>
			<xmin>710</xmin>
			<ymin>416</ymin>
			<xmax>816</xmax>
			<ymax>515</ymax>
		</bndbox>
	</object>
	<object>
		<name>stas</name>
		<pose>unspecified</pose>
		<truncated>0</truncated>
		<difficult>0</difficult>
		<bndbox>
			<xmin>803</xmin>
			<ymin>500</ymin>
			<xmax>846</xmax>
			<ymax>540</ymax>
		</bndbox>
	</object>
	<object>
		<name>stas</name>
		<pose>unspecified</pose>
		<truncated>0</truncated>
		<difficult>0</difficult>
		<bndbox>
			<xmin>831</xmin>
			<ymin>513</ymin>
			<xmax>887</xmax>
			<ymax>554</ymax>
		</bndbox>
	</object>
</annotation>